setup.py
synchrio/__init__.py
synchrio/wrapper.py
synchrio.egg-info/PKG-INFO
synchrio.egg-info/SOURCES.txt
synchrio.egg-info/dependency_links.txt
synchrio.egg-info/top_level.txt