Metadata-Version: 1.0
Name: synchrio
Version: 0.7
Summary: Wrapper class to run async code synchronously
Home-page: https://github.com/reshanie/synchrio/
Author: J Patrick Dill
Author-email: jamespatrickdill@gmail.com
License: GPLv3
Keywords: asyncio async blocking non-blocking
Platform: UNKNOWN
